{"name":"build-javascript","namedChunkGroups":{"app":{"name":"app","assets":[{"name":"webpack-runtime-80a99128641686e447cb.js","size":5187},{"name":"framework-eb2717286265eedfa6e8.js","size":141429},{"name":"app-d3f62e203229e207ab4d.js","size":69777}],"filteredAssets":0,"assetsSize":216393,"filteredAuxiliaryAssets":3,"auxiliaryAssetsSize":624801},"component---src-pages-404-js":{"name":"component---src-pages-404-js","assets":[{"name":"framework-eb2717286265eedfa6e8.js","size":141429},{"name":"commons-021fa91f488a8acf00d9.js","size":172049},{"name":"component---src-pages-404-js-fbfbfec0be0f8f22c5cf.js","size":726}],"filteredAssets":0,"assetsSize":314204,"filteredAuxiliaryAssets":3,"auxiliaryAssetsSize":1031045},"component---src-pages-core-team-js":{"name":"component---src-pages-core-team-js","assets":[{"name":"framework-eb2717286265eedfa6e8.js","size":141429},{"name":"commons-021fa91f488a8acf00d9.js","size":172049},{"name":"component---src-pages-core-team-js-fc3e0f50e7bb06b6eb16.js","size":1015}],"filteredAssets":0,"assetsSize":314493,"filteredAuxiliaryAssets":3,"auxiliaryAssetsSize":1032096},"component---src-pages-index-js":{"name":"component---src-pages-index-js","assets":[{"name":"framework-eb2717286265eedfa6e8.js","size":141429},{"name":"styles.8debf22be9a8356005c0.css","size":535},{"name":"commons-021fa91f488a8acf00d9.js","size":172049},{"name":"component---src-pages-index-js-f7ce95c561dd6d177c38.js","size":122672}],"filteredAssets":0,"assetsSize":436685,"filteredAuxiliaryAssets":6,"auxiliaryAssetsSize":2561482},"component---src-pages-junior-js":{"name":"component---src-pages-junior-js","assets":[{"name":"framework-eb2717286265eedfa6e8.js","size":141429},{"name":"commons-021fa91f488a8acf00d9.js","size":172049},{"name":"component---src-pages-junior-js-df318b514af0a005293d.js","size":652}],"filteredAssets":0,"assetsSize":314130,"filteredAuxiliaryAssets":3,"auxiliaryAssetsSize":1030769},"component---src-pages-terms-js":{"name":"component---src-pages-terms-js","assets":[{"name":"framework-eb2717286265eedfa6e8.js","size":141429},{"name":"commons-021fa91f488a8acf00d9.js","size":172049},{"name":"component---src-pages-terms-js-cba249241da075d5f1a0.js","size":14174}],"filteredAssets":0,"assetsSize":327652,"filteredAuxiliaryAssets":3,"auxiliaryAssetsSize":1092680}},"assetsByChunkName":{"app":["webpack-runtime-80a99128641686e447cb.js","framework-eb2717286265eedfa6e8.js","app-d3f62e203229e207ab4d.js"],"component---src-pages-404-js":["framework-eb2717286265eedfa6e8.js","commons-021fa91f488a8acf00d9.js","component---src-pages-404-js-fbfbfec0be0f8f22c5cf.js"],"component---src-pages-core-team-js":["framework-eb2717286265eedfa6e8.js","commons-021fa91f488a8acf00d9.js","component---src-pages-core-team-js-fc3e0f50e7bb06b6eb16.js"],"component---src-pages-index-js":["framework-eb2717286265eedfa6e8.js","styles.8debf22be9a8356005c0.css","commons-021fa91f488a8acf00d9.js","component---src-pages-index-js-f7ce95c561dd6d177c38.js"],"component---src-pages-junior-js":["framework-eb2717286265eedfa6e8.js","commons-021fa91f488a8acf00d9.js","component---src-pages-junior-js-df318b514af0a005293d.js"],"component---src-pages-terms-js":["framework-eb2717286265eedfa6e8.js","commons-021fa91f488a8acf00d9.js","component---src-pages-terms-js-cba249241da075d5f1a0.js"]},"childAssetsByChunkName":{}}